fontra/__init__.py
fontra/__main__.py
fontra/consts.py
fontra/fontdb.py
fontra/fzmatch.py
fontra/locutil.py
fontra/py.typed
fontra/typing.py
fontra-0.5.2.dist-info/LICENSE
fontra-0.5.2.dist-info/METADATA
fontra-0.5.2.dist-info/WHEEL
fontra-0.5.2.dist-info/entry_points.txt
fontra-0.5.2.dist-info/top_level.txt
fontra-0.5.2.dist-info/RECORD
