Metadata-Version: 2.1
Name: fontra
Version: 0.5.2
Summary: Font indexing and querying support like fontconfig.
Author-email: HivertMoZara <worldmozara@163.com>
License: MIT
Project-URL: Homepage, https://github.com/NCBM/fontra
Project-URL: Repository, https://github.com/NCBM/fontra
Classifier: Development Status :: 3 - Alpha
Classifier: Intended Audience :: Developers
Classifier: Intended Audience :: End Users/Desktop
Classifier: License :: OSI Approved :: MIT License
Classifier: Operating System :: MacOS
Classifier: Operating System :: Microsoft :: Windows
Classifier: Operating System :: Microsoft :: Windows :: Windows 10
Classifier: Operating System :: Microsoft :: Windows :: Windows 11
Classifier: Operating System :: POSIX :: Linux
Classifier: Programming Language :: Python :: 3
Classifier: Programming Language :: Python :: 3.9
Classifier: Programming Language :: Python :: 3.10
Classifier: Programming Language :: Python :: 3.11
Classifier: Programming Language :: Python :: 3.12
Classifier: Programming Language :: Python :: 3.13
Classifier: Programming Language :: Python :: 3.14
Classifier: Programming Language :: Python :: Implementation :: CPython
Classifier: Topic :: Software Development :: Libraries :: Python Modules
Classifier: Topic :: Software Development :: User Interfaces
Classifier: Topic :: Text Processing :: Fonts
Classifier: Topic :: Utilities
Classifier: Typing :: Typed
Requires-Python: >=3.9
License-File: LICENSE
Requires-Dist: freetype-py <3,>=2.5.1
Requires-Dist: typing-extensions <5,>=4.6.0
Requires-Dist: typer >=0.12.4
Requires-Dist: rich >=10.11
Provides-Extra: dev
Requires-Dist: freetype-py-stubs <3,>=2.5.1 ; extra == 'dev'
Provides-Extra: tools
Requires-Dist: fontTools >=4.53.1 ; extra == 'tools'
